rephraser/RePhraser.py
rephraser/Rephraser.ico
rephraser/Rephraser.png
rephraser/__init__.py
rephraser/__main__.py
rephraser/dark.qss
rephraser/login.qss
rephraser/images/__init__.py
rephraser/images/arrow-continue.png
rephraser/images/arrow-curve-180-left.png
rephraser/images/arrow-curve.png
rephraser/images/blue-folder-open-document.png
rephraser/images/clipboard-paste-document-text.png
rephraser/images/close.svg
rephraser/images/disk--pencil.png
rephraser/images/disk.png
rephraser/images/document-copy.png
rephraser/images/edit-alignment-center.png
rephraser/images/edit-alignment-justify.png
rephraser/images/edit-alignment-right.png
rephraser/images/edit-alignment.png
rephraser/images/edit-bold.png
rephraser/images/edit-color.png
rephraser/images/edit-italic.png
rephraser/images/edit-list-order.png
rephraser/images/edit-list.png
rephraser/images/edit-underline.png
rephraser/images/images.py
rephraser/images/images.qrc
rephraser/images/minimize.svg
rephraser/images/printer.png
rephraser/images/question.png
rephraser/images/scissors.png
rephraser/images/selection-input.png
rephraser/images/ui-tab--plus.png
rephraser/lib/AuthorEntry.py
rephraser/lib/AuthorTable.py
rephraser/lib/ClickableLabel.py
rephraser/lib/DarkPallete.py
rephraser/lib/Logger.py
rephraser/lib/ScrollBar.py
rephraser/lib/Stores.py
rephraser/lib/TextEdit.py
rephraser/lib/Toolbar.py
rephraser/lib/__init__.py
rephraser/lib/helper.py
rephraser/lib/qt_helper.py
rephraser-0.0.2.dist-info/METADATA
rephraser-0.0.2.dist-info/WHEEL
rephraser-0.0.2.dist-info/entry_points.txt
rephraser-0.0.2.dist-info/top_level.txt
rephraser-0.0.2.dist-info/RECORD
