Metadata-Version: 2.4
Name: rephraser
Version: 0.0.2
Summary: Rephrase essays and collage texts
Author-email: EliazarInso <deadbush225@gmail.com>
Project-URL: Homepage, https://github.com/Deadbush225/RePhrase
Keywords: rewrite,text,rephrase
Classifier: Development Status :: 4 - Beta
Classifier: Intended Audience :: End Users/Desktop
Classifier: Programming Language :: Python :: 3
Classifier: Programming Language :: Python :: 3.9
Classifier: Programming Language :: Python :: 3.10
Classifier: Programming Language :: Python :: 3.11
Classifier: License :: OSI Approved :: GNU Affero General Public License v3
Classifier: Operating System :: OS Independent
Classifier: Topic :: Text Editors
Classifier: Topic :: Text Processing
Requires-Python: >=3.9
Requires-Dist: PyQt5>=5.15.10
